{
  "products": [
    {
      "id": 1,
      "title": "Black Coat MockUp",
      "price": 290.90,
      "image": "https://slimages.macys.com/is/image/MCY/products/5/optimized/3921475_fpx.tif?op_sharpen=1&wid=700&hei=855&fit=fit,1"
    },
    {
      "id": 2,
      "title": "Sneakers MockUp",
      "price": 500.00,
      "image": "https://elements-cover-images-0.imgix.net/6e158932-cb02-4dcd-b601-b471fc9176b0?auto=compress&crop=edges&fit=crop&fm=jpeg&h=800&w=1200&s=6cbf20fc0d27f64d469ae6ab74ea3893"
    },
    {
      "id": 3,
      "title": "Training Shorts Mock",
      "price": 59.90,
      "image": "https://www.free-mockup.com/wp-content/uploads/edd/2019/04/Free-Training-Shorts-Mockup-01.jpg"
    },
    {
      "id": 4,
      "title": "Mug MockUp",
      "price": 40.00,
      "image": "https://mockuptree.com/wp-content/uploads/edd/2021/05/Free-Mug-Mockup-960x640.jpg"
    }
  ],
  "stock": [
    {
      "id": 1,
      "quantity": 12
    },
    {
      "id": 2,
      "quantity": 4
    },
    {
      "id": 3,
      "quantity": 10
    },
    {
      "id": 4,
      "quantity": 5
    }
  ]
}
